{"nodes": [{"id": "d_onedrive_desktop_atomquest_client_src_components_achievementmodal_jsx", "label": "AchievementModal.jsx", "file_type": "code", "source_file": "D:\\OneDrive\\Desktop\\atomquest\\client\\src\\components\\AchievementModal.jsx", "source_location": "L1"}, {"id": "components_achievementmodal_achievementmodal", "label": "AchievementModal()", "file_type": "code", "source_file": "D:\\OneDrive\\Desktop\\atomquest\\client\\src\\components\\AchievementModal.jsx", "source_location": "L4"}], "edges": [{"source": "d_onedrive_desktop_atomquest_client_src_components_achievementmodal_jsx", "target": "react", "relation": "imports_from", "confidence": "EXTRACTED", "source_file": "D:\\OneDrive\\Desktop\\atomquest\\client\\src\\components\\AchievementModal.jsx", "source_location": "L1", "weight": 1.0}, {"source": "d_onedrive_desktop_atomquest_client_src_components_achievementmodal_jsx", "target": "d_onedrive_desktop_atomquest_client_src_ui_tsx", "relation": "imports_from", "confidence": "EXTRACTED", "source_file": "D:\\OneDrive\\Desktop\\atomquest\\client\\src\\components\\AchievementModal.jsx", "source_location": "L2", "weight": 1.0}, {"source": "d_onedrive_desktop_atomquest_client_src_components_achievementmodal_jsx", "target": "components_achievementmodal_achievementmodal", "relation": "contains", "confidence": "EXTRACTED", "source_file": "D:\\OneDrive\\Desktop\\atomquest\\client\\src\\components\\AchievementModal.jsx", "source_location": "L4", "weight": 1.0}], "raw_calls": [{"caller_nid": "components_achievementmodal_achievementmodal", "callee": "useState", "is_member_call": false, "source_file": "D:\\OneDrive\\Desktop\\atomquest\\client\\src\\components\\AchievementModal.jsx", "source_location": "L6"}, {"caller_nid": "components_achievementmodal_achievementmodal", "callee": "useState", "is_member_call": false, "source_file": "D:\\OneDrive\\Desktop\\atomquest\\client\\src\\components\\AchievementModal.jsx", "source_location": "L7"}, {"caller_nid": "components_achievementmodal_achievementmodal", "callee": "useState", "is_member_call": false, "source_file": "D:\\OneDrive\\Desktop\\atomquest\\client\\src\\components\\AchievementModal.jsx", "source_location": "L8"}, {"caller_nid": "components_achievementmodal_achievementmodal", "callee": "useState", "is_member_call": false, "source_file": "D:\\OneDrive\\Desktop\\atomquest\\client\\src\\components\\AchievementModal.jsx", "source_location": "L9"}, {"caller_nid": "components_achievementmodal_achievementmodal", "callee": "useState", "is_member_call": false, "source_file": "D:\\OneDrive\\Desktop\\atomquest\\client\\src\\components\\AchievementModal.jsx", "source_location": "L10"}]}